masonite_ide_helper/__init__.py
masonite_ide_helper/generator.py
masonite_ide_helper/matchers.py
masonite_ide_helper/utils.py
masonite_ide_helper-0.1.0.dist-info/METADATA
masonite_ide_helper-0.1.0.dist-info/WHEEL
masonite_ide_helper-0.1.0.dist-info/top_level.txt
masonite_ide_helper-0.1.0.dist-info/RECORD
