Metadata-Version: 2.1
Name: masonite-ide-helper
Version: 0.1.0
Summary: A utility for generating Python type hinting stub files for Masonite ORM models.
Home-page: https://github.com/JarriqTheTechie/masonite_ide_helper
Author: Jarriq Rolle
Author-email: jrolle@baysidetechgroup.com
Classifier: Development Status :: 4 - Beta
Classifier: License :: OSI Approved :: MIT License
Classifier: Programming Language :: Python :: 3
Classifier: Programming Language :: Python :: 3.6
Classifier: Programming Language :: Python :: 3.7
Classifier: Programming Language :: Python :: 3.8
Classifier: Programming Language :: Python :: 3.9
Classifier: Programming Language :: Python :: 3.10
Classifier: Topic :: Software Development :: Libraries :: Python Modules
Classifier: Topic :: Utilities
Requires-Python: >=3.9
Requires-Dist: masonite-orm
